xy_youtuyun
