Metadata-Version: 1.0
Name: xy-youtuyun
Version: 7.0.0
Summary: Face AI Demo
Home-page: UNKNOWN
Author: KingHS
Author-email: 382771946@qq.com
License: MIT License
Keywords: xy_youtuyun,qcloud,pip3,face
Platform: any
